{"1":"Lobet Jehova! Lobet den Namen Jehovas! Lobet, ihr Knechte Jehovas,","2":"die ihr stehet im Hause Jehovas, in den Vorhöfen des Hauses unseres Gottes!","3":"Lobet Jehova! Denn gut ist Jehova; singet Psalmen seinem Namen! Denn er ist lieblich.","4":"Denn Jehova hat sich Jakob erwählt, Israel zu seinem Eigentum.","5":"Denn ich weiß, daß Jehova groß ist, und unser Herr groß vor allen Göttern.","6":"Alles, was Jehova wohlgefällt, tut er in den Himmeln und auf der Erde, in den Meeren und in allen Tiefen;","7":"der Dünste aufsteigen läßt vom Ende der Erde, der Blitze macht zum Regen, der den Wind herausführt aus seinen Vorratskammern;","8":"der die ErstgeborenenÄgyptens schlug vom Menschen bis zum Vieh,","9":"Zeichen und Wunder sandte in deine Mitte,Ägypten, wider den Pharao und wider alle seine Knechte;","10":"der große Nationen schlug und starke Könige tötete:","11":"Sihon, den König der Amoriter, und Og, den König von Basan, und alle Königreiche Kanaans;","12":"und ihr Land als Erbteil gab, als Erbteil seinem Volke Israel.","13":"Jehova, dein Name währt ewiglich, Jehova, dein Gedächtnis von Geschlecht zu Geschlecht.","14":"Denn Jehova wird sein Volk richten, und er wird sich's gereuen lassenüber seine Knechte.","15":"Die Götzen der Nationen sind Silber und Gold, ein Werk von Menschenhänden.","16":"Einen Mund haben sie und reden nicht; Augen haben sie und sehen nicht;","17":"Ohren haben sie und hören nicht; auch ist kein Odem in ihrem Munde.","18":"Ihnen gleich sind die, die sie machen, ein jeder, der auf sie vertraut.","19":"Haus Israel, preiset Jehova! Haus Aaron, preiset Jehova!","20":"Haus Levi, preiset Jehova! Die ihr Jehova fürchtet, preiset Jehova!","21":"Gepriesen sei Jehova von Zion aus, der zu Jerusalem wohnt! Lobet Jehova!"}